asiandrama/__init__.py
asiandrama/base/__init__.py
asiandrama/base/response.py
asiandrama/base/scraper.py
asiandrama/kshow123/__init__.py
asiandrama/kshow123/base.py
asiandrama/kshow123/search.py
asiandrama/kshow123/show.py
asiandrama/watchasian/__init__.py
asiandrama/watchasian/base.py
asiandrama/watchasian/drama.py
asiandrama/watchasian/search.py
asiandrama-0.0.1.dist-info/LICENSE
asiandrama-0.0.1.dist-info/METADATA
asiandrama-0.0.1.dist-info/WHEEL
asiandrama-0.0.1.dist-info/RECORD
