Metadata-Version: 2.1
Name: asiandrama
Version: 0.0.1
Summary: Korean shows and drama websites scraper library.
Author: TheBoringDude
Author-email: iamcoderx@gmail.com
Requires-Python: >=3.10,<4.0
Classifier: Programming Language :: Python :: 3
Classifier: Programming Language :: Python :: 3.10
Classifier: Programming Language :: Python :: 3.11
Requires-Dist: smaxpy (>=0.1.0,<0.2.0)
